README.txt
bootstrap.py
buildout.cfg
setup.py
src/z3hello/__init__.py
src/z3hello/configure.zcml
src/z3hello/views.py
src/z3hello.egg-info/PKG-INFO
src/z3hello.egg-info/SOURCES.txt
src/z3hello.egg-info/dependency_links.txt
src/z3hello.egg-info/not-zip-safe
src/z3hello.egg-info/requires.txt
src/z3hello.egg-info/top_level.txt
