Metadata-Version: 1.0
Name: z3hello
Version: 0.2
Summary: A Zope 3 hello app solely from eggs using zc.buildout
Home-page: http://svn.zope.org/Sandbox/baijum/z3hello/trunk
Author: Zope Corporation and Contributors
Author-email: zope3-dev@zope.org
License: ZPL 2.1
Platform: UNKNOWN
